berricake/__init__.py
berricake/berricake.cp312-win_amd64.pyd
berricake/calculation/shadow_analysis.cp312-win_amd64.pyd
berricake/components/__init__.py
berricake/components/epw_reader.cp312-win_amd64.pyd
berricake/components/output.cp312-win_amd64.pyd
berricake/components/pvsimple_module.cp312-win_amd64.pyd
berricake/components/surface_shadow_group.cp312-win_amd64.pyd
berricake/components/wind_module.cp312-win_amd64.pyd
berricake/core/__init__.py
berricake/core/base_module.cp312-win_amd64.pyd
berricake/core/link.cp312-win_amd64.pyd
berricake/core/manager.cp312-win_amd64.pyd
berricake/core/parser.cp312-win_amd64.pyd
berricake/core/time_controller.cp312-win_amd64.pyd
berricake/core/util.cp312-win_amd64.pyd
berricake/shadow_calc/__init__.py
berricake/shadow_calc/shadow_analysis.cp312-win_amd64.pyd
berricake-0.1.3.dist-info/METADATA
berricake-0.1.3.dist-info/WHEEL
berricake-0.1.3.dist-info/top_level.txt
berricake-0.1.3.dist-info/RECORD
