Metadata-Version: 2.4
Name: berricake
Version: 0.1.3
Summary: a modular simulation software. 
Author: zhc1993
Author-email: 
Keywords: python,simulate,berricake,windows
Classifier: Development Status :: 1 - Planning
Classifier: Intended Audience :: Developers
Classifier: Programming Language :: Python :: 3
Classifier: Operating System :: Microsoft :: Windows
Requires-Dist: numpy
Requires-Dist: scipy
Requires-Dist: colorama
Dynamic: author
Dynamic: classifier
Dynamic: description
Dynamic: description-content-type
Dynamic: keywords
Dynamic: requires-dist
Dynamic: summary
